{
	"name": "Google Sans_85% (iOS10-12)",
	"package": "com.evynw.fontgooglesans8512",
	"author": "Alex (@Alexman1979)",
	"version": "1.0",
	"dependency": "N/A",
	"minOSVersion": "10.0",
	"maxOSVersion": "12.1.2",
	"otheriOS": "untested",
	"description": "<div><strong>85% size. Install 'Google Sans' for normal character size</strong><br><br>Installed to: /Library/Themes/[fontname].theme/<br><br><strong>Need help?</strong> Link to tutorials in my pinned tweet</div>",
  	"changelog": {
	    "1.0": [
	      "Initial release"
	    ]
  	},
	"screenshots": {
		"ss.png": ""
	},
	"links": {}
}
